<?xml version="1.0"?>
<?iotk version="1.2.0"?>
<?iotk file_version="1.0"?>
<?iotk binary="F"?>
<?iotk qe_syntax="F"?>
<Root>
  <PM_HEADER>
    <DONE_IRR type="logical" size="1">
T
    </DONE_IRR>
  </PM_HEADER>
  <PARTIAL_MATRIX>
    <PARTIAL_DYN type="complex" size="36">
-2.531548620808330E+001,-4.838785000187422E-007
-2.383998488907015E-001,-3.576963910375735E-006
-1.910450669129026E-001, 1.273607457390575E-006
 0.000000000000000E+000, 0.000000000000000E+000
 0.000000000000000E+000, 0.000000000000000E+000
 0.000000000000000E+000, 0.000000000000000E+000
-2.387071245100554E-001, 2.963614649719131E-006
-2.467524626564845E+001,-1.546517300978836E-006
 2.216794795083969E-001, 6.268242147626494E-007
 0.000000000000000E+000, 0.000000000000000E+000
 0.000000000000000E+000, 0.000000000000000E+000
 0.000000000000000E+000, 0.000000000000000E+000
-1.875367224288412E-001,-1.924113814555515E-006
 2.223754833027684E-001,-6.206843577566153E-007
-2.509197932108412E+001,-4.682497446785370E-007
 0.000000000000000E+000, 0.000000000000000E+000
 0.000000000000000E+000, 0.000000000000000E+000
 0.000000000000000E+000, 0.000000000000000E+000
 9.121766807543141E-006,-3.074903210677591E-001
 7.683568483917903E-007, 1.892647872644970E-002
 1.842605575706205E-005,-2.830085183132142E-001
 0.000000000000000E+000, 0.000000000000000E+000
 0.000000000000000E+000, 0.000000000000000E+000
 0.000000000000000E+000, 0.000000000000000E+000
-1.153540755088529E-005, 2.161947402784974E-001
-3.766805817608674E-005,-7.357865687718246E-002
 5.159152546274255E-006,-1.620898977848504E-001
 0.000000000000000E+000, 0.000000000000000E+000
 0.000000000000000E+000, 0.000000000000000E+000
 0.000000000000000E+000, 0.000000000000000E+000
-3.116989634343754E-005,-1.357259428619936E-001
-2.118062818518949E-005, 4.020828977713603E-002
 1.592156129517467E-005, 2.800397630055236E-001
 0.000000000000000E+000, 0.000000000000000E+000
 0.000000000000000E+000, 0.000000000000000E+000
 0.000000000000000E+000, 0.000000000000000E+000
    </PARTIAL_DYN>
    <PARTIAL_ZUE type="complex" size="18">
-3.671986153523763E-006,-1.912106332769170E-001
-3.339635918866220E-006,-1.211875544680759E-001
 2.922229123180969E-006, 2.304341859910304E-001
 0.000000000000000E+000, 0.000000000000000E+000
 0.000000000000000E+000, 0.000000000000000E+000
 0.000000000000000E+000, 0.000000000000000E+000
 5.306451290327089E-006, 1.263046216303249E-001
 3.242284369772974E-006, 1.920113637782574E-001
-3.218249921092321E-006, 4.668207315617220E-003
 0.000000000000000E+000, 0.000000000000000E+000
 0.000000000000000E+000, 0.000000000000000E+000
 0.000000000000000E+000, 0.000000000000000E+000
 1.438470502479136E-006, 6.931891552270827E-002
-2.323946482157228E-006,-1.218239331403523E-001
 5.711390854061071E-007, 1.199608686598100E-001
 0.000000000000000E+000, 0.000000000000000E+000
 0.000000000000000E+000, 0.000000000000000E+000
 0.000000000000000E+000, 0.000000000000000E+000
    </PARTIAL_ZUE>
  </PARTIAL_MATRIX>
</Root>

