<?xml version="1.0"?>
<?iotk version="1.2.0"?>
<?iotk file_version="1.0"?>
<?iotk binary="F"?>
<?iotk qe_syntax="F"?>
<Root>
  <PM_HEADER>
    <DONE_IRR type="logical" size="1">
T
    </DONE_IRR>
  </PM_HEADER>
  <PARTIAL_MATRIX>
    <PARTIAL_DYN type="complex" size="36">
 7.583886846894009E+000,-3.584860926803442E-033
 4.347462288920062E-001,-4.347462288920032E-001
 9.879152422993765E-017, 5.292443609548016E-017
 1.143588781530389E-001,-9.124941657455249E-017
 1.336825194312346E-001,-2.418930726206929E-017
-5.208132677217258E-016, 4.879137312703205E-016
 4.347462288920054E-001, 4.347462288920033E-001
 2.183020189900804E+000,-1.648803008254589E-035
 2.530896299515313E-002, 4.760399324668135E-019
 2.135954919547443E-016,-2.014570736037247E-016
-4.072376492714413E-016, 1.074954031991943E-016
 3.204777157579430E-002, 4.682194758723194E-019
-1.344442875392882E-017,-2.121066117184174E-016
 2.530896299515316E-002,-4.760399324668133E-019
 1.579785270429734E+000,-5.670961105992991E-035
 3.220130427664208E-001,-7.567592700289257E-001
 1.082467449009528E-015,-1.387778780781446E-017
 2.789125762482550E-002,-5.529897889941754E-021
 1.143588781530387E-001, 9.124941657455251E-017
 6.716194159351430E-017, 5.572719622949759E-017
 3.220130427664220E-001, 7.567592700289258E-001
 5.908234292807328E+000, 1.225297031289328E-033
 7.850105275198693E-002, 5.221507162204783E-018
 2.359223927328458E-016, 4.718447854656915E-016
 1.336825194312346E-001, 2.418930726206929E-017
-4.746144218650500E-016, 3.928776498970118E-017
 2.359223927328458E-016, 1.942890293094024E-016
 7.850105275198693E-002,-5.221507162204779E-018
 5.908234292807326E+000, 2.753805538065733E-032
-7.567592700289210E-001,-3.220130427664183E-001
-3.457648532735783E-016,-3.347992183570516E-016
 3.204777157579428E-002,-4.682194758723195E-019
 2.789125762482550E-002, 5.529897889941871E-021
 9.714451465470120E-016,-2.775557561562891E-017
-7.567592700289213E-001, 3.220130427664182E-001
 1.579785270429739E+000,-2.008959053878110E-035
    </PARTIAL_DYN>
  </PARTIAL_MATRIX>
</Root>

