<?xml version="1.0"?>
<?iotk version="1.2.0"?>
<?iotk file_version="1.0"?>
<?iotk binary="F"?>
<?iotk qe_syntax="F"?>
<Root>
  <PM_HEADER>
    <DONE_IRR type="logical" size="1">
T
    </DONE_IRR>
  </PM_HEADER>
  <PARTIAL_MATRIX>
    <PARTIAL_DYN type="complex" size="36">
-2.196434859659688E+001, 2.763652911351885E-003
-8.426984409807189E-002,-3.766667219496544E-001
 0.000000000000000E+000, 0.000000000000000E+000
 0.000000000000000E+000, 0.000000000000000E+000
 0.000000000000000E+000, 0.000000000000000E+000
 0.000000000000000E+000, 0.000000000000000E+000
-8.588175054651448E-002, 3.802484243060933E-001
-2.190737356192895E+001,-2.764501614066385E-003
 0.000000000000000E+000, 0.000000000000000E+000
 0.000000000000000E+000, 0.000000000000000E+000
 0.000000000000000E+000, 0.000000000000000E+000
 0.000000000000000E+000, 0.000000000000000E+000
-7.702038636273334E-003,-2.317583123841760E-002
-7.124506509132622E-002,-9.120866595303057E-002
 0.000000000000000E+000, 0.000000000000000E+000
 0.000000000000000E+000, 0.000000000000000E+000
 0.000000000000000E+000, 0.000000000000000E+000
 0.000000000000000E+000, 0.000000000000000E+000
-2.514228178156630E-001,-1.321655619062086E-001
-2.308550807984913E-001,-7.750871717654662E-002
 0.000000000000000E+000, 0.000000000000000E+000
 0.000000000000000E+000, 0.000000000000000E+000
 0.000000000000000E+000, 0.000000000000000E+000
 0.000000000000000E+000, 0.000000000000000E+000
 9.078690068383626E-001, 3.411826494807534E+000
-2.933855223121762E-002,-6.412251113807421E-001
 0.000000000000000E+000, 0.000000000000000E+000
 0.000000000000000E+000, 0.000000000000000E+000
 0.000000000000000E+000, 0.000000000000000E+000
 0.000000000000000E+000, 0.000000000000000E+000
 4.941525598064384E-001,-4.211538120339176E-002
 3.349251313468494E+000,-1.175401021242187E+000
 0.000000000000000E+000, 0.000000000000000E+000
 0.000000000000000E+000, 0.000000000000000E+000
 0.000000000000000E+000, 0.000000000000000E+000
 0.000000000000000E+000, 0.000000000000000E+000
    </PARTIAL_DYN>
  </PARTIAL_MATRIX>
</Root>

